README.txt
setup.py
djftpd/__init__.py
djftpd/authorizer.py
djftpd.egg-info/PKG-INFO
djftpd.egg-info/SOURCES.txt
djftpd.egg-info/dependency_links.txt
djftpd.egg-info/not-zip-safe
djftpd.egg-info/requires.txt
djftpd.egg-info/top_level.txt
djftpd/management/__init__.py
djftpd/management/commands/__init__.py
djftpd/management/commands/startftpserver.py
djftpdtests/__init__.py
djftpdtests/manage.py
djftpdtests/settings.py
djftpdtests/urls.py