Metadata-Version: 1.0
Name: djftpd
Version: 0.3.0
Summary: FTP-server authenticating against django user database.
Home-page: http://bitbucket.org/weholt/djftpd
Author: Thomas Weholt
Author-email: thomas@weholt.org
License: GPL v3.0
Platform: UNKNOWN
